{
    "configurations": [
        {
            "name": "Linux",
            "includePath": [
                "${workspaceFolder}/**",
                "/usr/local/include/**",
                "/usr/local/include/eigen3/**",
                "${workspaceFolder}/Thirdparty/manif/include/**",
                "${workspaceFolder}/imu_align/include/**",
                "${workspaceFolder}/Thirdparty/GeographicLib-1.51/include/**",
                "${workspaceFolder}/Thirdparty/manif/include/**"
            ],
            "defines": [],
            "compilerPath": "/usr/bin/gcc",
            "cStandard": "gnu17",
            "cppStandard": "gnu++14",
            "intelliSenseMode": "linux-gcc-x64"
        }
    ],
    "version": 4
}